<annotation verified="yes">
                                    <folder>Annotation</folder>
                                    <filename>78b7816b-3376-4a39-9b57-055d1d662d3b-2</filename>
                                    <path>C:\Users\tinzha\Documents\EY\handwriting\trainjpg_output\JPEGImages\78b7816b-3376-4a39-9b57-055d1d662d3b-2.jpg</path>
                                    <source>
                                        <database>Unknown</database>
                                    </source>
                                    <size>
                                        <width>1749</width>
                                        <height>2214</height>
                                        <depth>3</depth>
                                    </size>
                                    <segmented>0</segmented>
                                    <object>
                                            <name>signature</name>
                                            <pose>Unspecified</pose>
                                            <bndbox>
                                                <xmin>265</xmin>
                                                <ymin>351</ymin>
                                                <xmax>463</xmax>
                                                <ymax>522</ymax>
                                            </bndbox>
                                    </object>
                                    
                                    <object>
                                            <name>signature</name>
                                            <pose>Unspecified</pose>
                                            <bndbox>
                                                <xmin>194</xmin>
                                                <ymin>729</ymin>
                                                <xmax>697</xmax>
                                                <ymax>867</ymax>
                                            </bndbox>
                                    </object>
                                    
                                    <object>
                                            <name>signature</name>
                                            <pose>Unspecified</pose>
                                            <bndbox>
                                                <xmin>221</xmin>
                                                <ymin>546</ymin>
                                                <xmax>729</xmax>
                                                <ymax>652</ymax>
                                            </bndbox>
                                    </object>
                                    
                                    <object>
                                            <name>others</name>
                                            <pose>Unspecified</pose>
                                            <bndbox>
                                                <xmin>1246</xmin>
                                                <ymin>785</ymin>
                                                <xmax>1542</xmax>
                                                <ymax>859</ymax>
                                            </bndbox>
                                    </object>
                                    </annotation>